Workbook

Sheet Raw_Data
A1: Order ID | B1: Date | C1: Month | D1: Region | E1: City | F1: Sales Executive | G1: Product Category | H1: Product Name | I1: Units Sold | J1: Selling Price (₹) | K1: Revenue (₹) | L1: Cost (₹) | M1: Profit (₹) | N1: Customer Type | O1: Sales Channel | P1: Target Sales (₹) | Q1: Achievement % | R1: Growth %
A2: ORD-1001 | B2: 01-01-2024 | C2: Jan-2024 | D2: North | E2: Delhi | F2: Vikram Singh | G2: Furniture | H2: Desk | I2: 5 | J2: 471.28 | K2: 2356.4 | L2: 1296.02 | M2: 1060.38 | N2: New | O2: Offline | P2: 1922.57 | Q2: 122.57
A3: ORD-1002 | B3: 01-01-2024 | C3: Jan-2024 | D3: North | E3: Delhi | F3: Sneha Reddy | G3: Electronics | H3: Smartphone | I3: 18 | J3: 787.12 | K3: 14168.16 | L3: 8500.9 | M3: 5667.26 | N3: Existing | O3: Offline | P3: 17068.6 | Q3: 83.01
A4: ORD-1003 | B4: 01-01-2024 | C4: Jan-2024 | D4: North | E4: Delhi | F4: Amit Kumar | G4: Apparel | H4: T-Shirt | I4: 5 | J4: 37.72 | K4: 188.6 | L4: 84.87 | M4: 103.73 | N4: Existing | O4: Online | P4: 159.63 | Q4: 118.15
A5: ORD-1004 | B5: 02-01-2024 | C5: Jan-2024 | D5: East | E5: Bhubaneswar | F5: Kavita Rao | G5: Apparel | H5: Jacket | I5: 15 | J5: 120.87 | K5: 1813.05 | L5: 815.87 | M5: 997.18 | N5: Existing | O5: Online | P5: 1950.88 | Q5: 92.93
A6: ORD-1005 | B6: 03-01-2024 | C6: Jan-2024 | D6: East | E6: Patna | F6: Sneha Reddy | G6: Electronics | H6: Laptop | I6: 8 | J6: 1265.54 | K6: 10124.32 | L6: 6074.59 | M6: 4049.73 | N6: New | O6: Online | P6: 12485.73 | Q6: 81.09
A7: ORD-1006 | B7: 03-01-2024 | C7: Jan-2024 | D7: West | E7: Ahmedabad | F7: Pooja Joshi | G7: Apparel | H7: Formal Shirt | I7: 12 | J7: 77.68 | K7: 932.16 | L7: 419.47 | M7: 512.69 | N7: Existing | O7: Online | P7: 1029.63 | Q7: 90.53
A8: ORD-1007 | B8: 03-01-2024 | C8: Jan-2024 | D8: South | E8: Hyderabad | F8: Sneha Reddy | G8: Furniture | H8: Cabinet | I8: 13 | J8: 286.2 | K8: 3720.6 | L8: 2046.33 | M8: 1674.27 | N8: New | O8: Offline | P8: 4544.44 | Q8: 81.87
A9: ORD-1008 | B9: 04-01-2024 | C9: Jan-2024 | D9: South | E9: Chennai | F9: Deepa Nair | G9: Software | H9: Analytics Pro | I9: 3 | J9: 2355.49 | K9: 7066.47 | L9: 2119.94 | M9: 4946.53 | N9: Existing | O9: Online | P9: 7968.99 | Q9: 88.67
A10: ORD-1009 | B10: 05-01-2024 | C10: Jan-2024 | D10: West | E10: Mumbai | F10: Vikram Singh | G10: Furniture | H10: Desk | I10: 18 | J10: 453.51 | K10: 8163.18 | L10: 4489.75 | M10: 3673.43 | N10: Existing | O10: Offline | P10: 8008.07 | Q10: 101.94
A11: ORD-1010 | B11: 05-01-2024 | C11: Jan-2024 | D11: South | E11: Hyderabad | F11: Pooja Joshi | G11: Electronics | H11: Laptop | I11: 4 | J11: 1116.68 | K11: 4466.72 | L11: 2680.03 | M11: 1786.69 | N11: New | O11: Offline | P11: 4905.37 | Q11: 91.06
A12: ORD-1011 | B12: 06-01-2024 | C12: Jan-2024 | D12: West | E12: Pune | F12: Pooja Joshi | G12: Apparel | H12: Jacket | I12: 4 | J12: 124.36 | K12: 497.44 | L12: 223.85 | M12: 273.59 | N12: Existing | O12: Offline | P12: 425.7 | Q12: 116.85
A13: ORD-1012 | B13: 06-01-2024 | C13: Jan-2024 | D13: West | E13: Mumbai | F13: Pooja Joshi | G13: Electronics | H13: Tablet | I13: 17 | J13: 631.44 | K13: 10734.48 | L13: 6440.69 | M13: 4293.79 | N13: New | O13: Offline | P13: 13105.03 | Q13: 81.91
... A658: ORD-1657 | B658: 30-12-2024 | C658: Dec-2024 | D658: North | E658: Chandigarh | F658: Deepa Nair | G658: Electronics | H658: Smartwatch | I658: 5 | J658: 284.16 | K658: 1420.8 | L658: 852.48 | M658: 568.32 | N658: New | O658: Offline | P658: 1489.32 | Q658: 95.4

Sheet Cleaned_Data
A1: Order ID | B1: Date | C1: Month | D1: Region | E1: City | F1: Sales Executive | G1: Product Category | H1: Product Name | I1: Units Sold | J1: Selling Price (₹) | K1: Revenue (₹) | L1: Cost (₹) | M1: Profit (₹) | N1: Customer Type | O1: Sales Channel | P1: Target Sales (₹) | Q1: Achievement % | R1: Profit Margin %
A2: =Raw_Data!A2 | B2: =Raw_Data!B2 | C2: =Raw_Data!C2 | D2: =Raw_Data!D2 | E2: =Raw_Data!E2 | F2: =Raw_Data!F2 | G2: =Raw_Data!G2 | H2: =Raw_Data!H2 | ... P2: =Raw_Data!P2 | R2: =IFERROR(Cleaned_Data!M2/Cleaned_Data!K2,0)
A3: =Raw_Data!A3 | B3: =Raw_Data!B3 | C3: =Raw_Data!C3 | D3: =Raw_Data!D3 | E3: =Raw_Data!E3 | F3: =Raw_Data!F3 | G3: =Raw_Data!G3 | H3: =Raw_Data!H3 | ... P3: =Raw_Data!P3 | R3: =IFERROR(Cleaned_Data!M3/Cleaned_Data!K3,0)
A4: =Raw_Data!A4 | B4: =Raw_Data!B4 | C4: =Raw_Data!C4 | D4: =Raw_Data!D4 | E4: =Raw_Data!E4 | F4: =Raw_Data!F4 | G4: =Raw_Data!G4 | H4: =Raw_Data!H4 | ... P4: =Raw_Data!P4 | R4: =IFERROR(Cleaned_Data!M4/Cleaned_Data!K4,0)
A5: =Raw_Data!A5 | B5: =Raw_Data!B5 | C5: =Raw_Data!C5 | D5: =Raw_Data!D5 | E5: =Raw_Data!E5 | F5: =Raw_Data!F5 | G5: =Raw_Data!G5 | H5: =Raw_Data!H5 | ... P5: =Raw_Data!P5 | R5: =IFERROR(Cleaned_Data!M5/Cleaned_Data!K5,0)
A6: =Raw_Data!A6 | B6: =Raw_Data!B6 | C6: =Raw_Data!C6 | D6: =Raw_Data!D6 | E6: =Raw_Data!E6 | F6: =Raw_Data!F6 | G6: =Raw_Data!G6 | H6: =Raw_Data!H6 | ... P6: =Raw_Data!P6 | R6: =IFERROR(Cleaned_Data!M6/Cleaned_Data!K6,0)
A7: =Raw_Data!A7 | B7: =Raw_Data!B7 | C7: =Raw_Data!C7 | D7: =Raw_Data!D7 | E7: =Raw_Data!E7 | F7: =Raw_Data!F7 | G7: =Raw_Data!G7 | H7: =Raw_Data!H7 | ... P7: =Raw_Data!P7 | R7: =IFERROR(Cleaned_Data!M7/Cleaned_Data!K7,0)
A8: =Raw_Data!A8 | B8: =Raw_Data!B8 | C8: =Raw_Data!C8 | D8: =Raw_Data!D8 | E8: =Raw_Data!E8 | F8: =Raw_Data!F8 | G8: =Raw_Data!G8 | H8: =Raw_Data!H8 | ... P8: =Raw_Data!P8 | R8: =IFERROR(Cleaned_Data!M8/Cleaned_Data!K8,0)
A9: =Raw_Data!A9 | B9: =Raw_Data!B9 | C9: =Raw_Data!C9 | D9: =Raw_Data!D9 | E9: =Raw_Data!E9 | F9: =Raw_Data!F9 | G9: =Raw_Data!G9 | H9: =Raw_Data!H9 | ... P9: =Raw_Data!P9 | R9: =IFERROR(Cleaned_Data!M9/Cleaned_Data!K9,0)
A10: =Raw_Data!A10 | B10: =Raw_Data!B10 | C10: =Raw_Data!C10 | D10: =Raw_Data!D10 | E10: =Raw_Data!E10 | F10: =Raw_Data!F10 | G10: =Raw_Data!G10 | H10: =Raw_Data!H10 | ... P10: =Raw_Data!P10 | R10: =IFERROR(Cleaned_Data!M10/Cleaned_Data!K10,0)
A11: =Raw_Data!A11 | B11: =Raw_Data!B11 | C11: =Raw_Data!C11 | D11: =Raw_Data!D11 | E11: =Raw_Data!E11 | F11: =Raw_Data!F11 | G11: =Raw_Data!G11 | H11: =Raw_Data!H11 | ... P11: =Raw_Data!P11 | R11: =IFERROR(Cleaned_Data!M11/Cleaned_Data!K11,0)
A12: =Raw_Data!A12 | B12: =Raw_Data!B12 | C12: =Raw_Data!C12 | D12: =Raw_Data!D12 | E12: =Raw_Data!E12 | F12: =Raw_Data!F12 | G12: =Raw_Data!G12 | H12: =Raw_Data!H12 | ... P12: =Raw_Data!P12 | R12: =IFERROR(Cleaned_Data!M12/Cleaned_Data!K12,0)
A13: =Raw_Data!A13 | B13: =Raw_Data!B13 | C13: =Raw_Data!C13 | D13: =Raw_Data!D13 | E13: =Raw_Data!E13 | F13: =Raw_Data!F13 | G13: =Raw_Data!G13 | H13: =Raw_Data!H13 | ... P13: =Raw_Data!P13 | R13: =IFERROR(Cleaned_Data!M13/Cleaned_Data!K13,0)
... A658: =Raw_Data!A658 | B658: =Raw_Data!B658 | C658: =Raw_Data!C658 | D658: =Raw_Data!D658 | E658: =Raw_Data!E658 | F658: =Raw_Data!F658 | G658: =Raw_Data!G658 | H658: =Raw_Data!H658 | ... P658: =Raw_Data!P658 | R658: =IFERROR(Cleaned_Data!M658/Cleaned_Data!K658,0)

Sheet KPI_Summary
A1: 📊 SALES & REVENUE GROWTH TRACKER — KPI SUMMARY (2024)
A3: KEY PERFORMANCE INDICATORS
A4: Total Revenue (₹) | C4: Total Profit (₹) | E4: Total Units Sold | G4: Total Orders
A5: =SUM(Cleaned_Data!K2:K658) | C5: =SUM(Cleaned_Data!M2:M658) | E5: =SUM(Cleaned_Data!I2:I658) | G5: =COUNTA(Cleaned_Data!A2:A658)
A7: Avg Profit Margin | C7: Avg Achievement % | E7: Online Revenue | G7: Offline Revenue
A8: =AVERAGE(Cleaned_Data!R2:R658) | C8: =AVERAGE(Cleaned_Data!Q2:Q658) | E8: =SUMIF(Cleaned_Data!O2:O658,"Online",Cleaned_Data!K2:K658) | G8: =SUMIF(Cleaned_Data!O2:O658,"Offline",Cleaned_Data!K2:K658)
A14: REVENUE BY REGION | F14: REVENUE BY PRODUCT CATEGORY
A15: Region | B15: Total Revenue (₹) | C15: Total Profit (₹) | D15: Orders Count | F15: Category | G15: Revenue (₹) | H15: Profit (₹)
A16: North | B16: =SUMIF(Cleaned_Data!D:D,"North",Cleaned_Data!K:K) | C16: =SUMIF(Cleaned_Data!D:D,"North",Cleaned_Data!M:M) | D16: =COUNTIF(Cleaned_Data!D:D,"North") | F16: Electronics | G16: =SUMIF(Cleaned_Data!G:G,"Electronics",Cleaned_Data!K:K) | H16: =SUMIF(Cleaned_Data!G:G,"Electronics",Cleaned_Data!M:M)
A17: South | B17: =SUMIF(Cleaned_Data!D:D,"South",Cleaned_Data!K:K) | C17: =SUMIF(Cleaned_Data!D:D,"South",Cleaned_Data!M:M) | D17: =COUNTIF(Cleaned_Data!D:D,"South") | F17: Furniture | G17: =SUMIF(Cleaned_Data!G:G,"Furniture",Cleaned_Data!K:K) | H17: =SUMIF(Cleaned_Data!G:G,"Furniture",Cleaned_Data!M:M)
A18: East | B18: =SUMIF(Cleaned_Data!D:D,"East",Cleaned_Data!K:K) | C18: =SUMIF(Cleaned_Data!D:D,"East",Cleaned_Data!M:M) | D18: =COUNTIF(Cleaned_Data!D:D,"East") | F18: Apparel | G18: =SUMIF(Cleaned_Data!G:G,"Apparel",Cleaned_Data!K:K) | H18: =SUMIF(Cleaned_Data!G:G,"Apparel",Cleaned_Data!M:M)
A19: West | B19: =SUMIF(Cleaned_Data!D:D,"West",Cleaned_Data!K:K) | C19: =SUMIF(Cleaned_Data!D:D,"West",Cleaned_Data!M:M) | D19: =COUNTIF(Cleaned_Data!D:D,"West") | F19: Software | G19: =SUMIF(Cleaned_Data!G:G,"Software",Cleaned_Data!K:K) | H19: =SUMIF(Cleaned_Data!G:G,"Software",Cleaned_Data!M:M)

Sheet Formulas_Guide
A1: Excel Formulas Used in This Project
A2: Formula | B2: Syntax | C2: Purpose | D2: Example
A3: SUM | B3: =SUM(range) | C3: Adds all values in a range | D3: =SUM(K2:K500)
A4: SUMIFS | B4: =SUMIFS(sum_range,criteria_range1,c1) | C4: Conditional sum with multiple criteria | D4: =SUMIFS(K:K,D:D,"North")
A5: IF | B5: =IF(condition,true,false) | C5: Returns value based on condition | D5: =IF(Q2>=100%,"Met","Not Met")
A6: IFERROR | B6: =IFERROR(formula,fallback) | C6: Handles errors gracefully | D6: =IFERROR(K2/P2,0)
A7: COUNTIFS | B7: =COUNTIFS(range1,criteria1,...) | C7: Count rows meeting multiple criteria | D7: =COUNTIFS(D:D,"South",O:O,"Online")
A8: XLOOKUP | B8: =XLOOKUP(val,lookup,return) | C8: Modern lookup — replaces VLOOKUP | D8: =XLOOKUP(A2,Raw_Data!A:A,Raw_Data!F:F)
A9: VLOOKUP | B9: =VLOOKUP(val,table,col,0) | C9: Vertical lookup in a table | D9: =VLOOKUP(A2,Raw_Data!A:F,6,0)
A10: INDEX-MATCH | B10: =INDEX(return,MATCH(val,lookup,0)) | C10: Flexible 2-way lookup | D10: =INDEX(F:F,MATCH(A2,A:A,0))
A11: Revenue | B11: =Units_Sold * Selling_Price | C11: Basic revenue calculation | D11: =I2*J2
A12: Profit | B12: =Revenue - Cost | C12: Net profit per transaction | D12: =K2-L2
A13: Profit% | B13: =Profit / Revenue | C13: Profit margin percentage | D13: =M2/K2
A14: Achievement% | B14: =Revenue / Target | C14: Actual vs target performance | D14: =K2/P2
A15: MoM Growth% | B15: =(Current-Previous)/Previous | C15: Month-over-month revenue growth | D15: =(C3-C2)/C2
A16: AVERAGE | B16: =AVERAGE(range) | C16: Mean value of a range | D16: =AVERAGE(Q2:Q500)
A17: FORECAST | B17: =FORECAST.ETS(target,values,dates) | C17: Predict future revenue using history | D17: =FORECAST.ETS(13,B2:B13,A2:A13)

Sheet Dashboard
A1: 📊 SALES & REVENUE GROWTH TRACKER DASHBOARD | 2024
A2: Real-Time Sales Analytics · Revenue · Profitability · Regional & Category Performance
A4: TOTAL REVENUE | E4: TOTAL PROFIT | I4: TOTAL ORDERS | M4: UNITS SOLD | Q4: AVG ACHIEVEMENT
A5: =SUM(Cleaned_Data!K2:K658) | E5: =SUM(Cleaned_Data!M2:M658) | I5: =COUNTA(Cleaned_Data!A2:A658) | M5: =SUM(Cleaned_Data!I2:I658) | Q5: =AVERAGE(Cleaned_Data!Q2:Q658)
A55: Region | B55: Revenue | C55: Profit
A56: North | B56: =SUMIF(Cleaned_Data!D:D,"North",Cleaned_Data!K:K) | C56: =SUMIF(Cleaned_Data!D:D,"North",Cleaned_Data!M:M)
A57: South | B57: =SUMIF(Cleaned_Data!D:D,"South",Cleaned_Data!K:K) | C57: =SUMIF(Cleaned_Data!D:D,"South",Cleaned_Data!M:M)
A58: East | B58: =SUMIF(Cleaned_Data!D:D,"East",Cleaned_Data!K:K) | C58: =SUMIF(Cleaned_Data!D:D,"East",Cleaned_Data!M:M)
A59: West | B59: =SUMIF(Cleaned_Data!D:D,"West",Cleaned_Data!K:K) | C59: =SUMIF(Cleaned_Data!D:D,"West",Cleaned_Data!M:M)
A62: Category | B62: Revenue
A63: Electronics | B63: =SUMIF(Cleaned_Data!G:G,"Electronics",Cleaned_Data!K:K)
A64: Furniture | B64: =SUMIF(Cleaned_Data!G:G,"Furniture",Cleaned_Data!K:K)
A65: Apparel | B65: =SUMIF(Cleaned_Data!G:G,"Apparel",Cleaned_Data!K:K)
A66: Software | B66: =SUMIF(Cleaned_Data!G:G,"Software",Cleaned_Data!K:K)
A68: Channel | B68: Revenue
A69: Online | B69: =SUMIF(Cleaned_Data!O:O,"Online",Cleaned_Data!K:K)
A70: Offline | B70: =SUMIF(Cleaned_Data!O:O,"Offline",Cleaned_Data!K:K)

Sheet Pivot_Guide
A1: Pivot Table & Dashboard — Step-by-Step Guide
A2: Pivot Table Name | B2: Rows Field | C2: Columns Field | D2: Values Field | E2: Filter/Slicer
A3: Revenue by Region | B3: Region | C3: — | D3: Revenue (Sum) | E3: Month, Channel
A4: Revenue by Category | B4: Product Category | C4: — | D4: Revenue (Sum) | E4: Region, Month
A5: Sales by Executive | B5: Sales Executive | C5: — | D5: Revenue (Sum) | E5: Region, Category
A6: Monthly Revenue Trend | B6: Month | C6: — | D6: Revenue (Sum) | E6: Region, Category
A7: Channel-wise Performance | B7: Sales Channel | C7: — | D7: Revenue (Sum) | E7: Region, Month
A8: Customer Type Analysis | B8: Customer Type | C8: — | D8: Revenue (Sum) | E8: Region, Category
A9: Product Profitability | B9: Product Name | C9: — | D9: Profit (Sum) | E9: Category, Region
A10: Target vs Achievement | B10: Sales Executive | C10: Month | D10: Achievement % | E10: Region
A14: HOW TO CREATE A PIVOT TABLE
A15: 1. Click anywhere in the Cleaned_Data sheet.
A16: 2. Go to Insert tab → Click 'PivotTable'.
A17: 3. Select 'New Worksheet' and click OK.
A18: 4. Drag fields from PivotTable Field List (see table above for which fields go where).
A19: 5. Right-click on Pivot → 'Insert Slicer' to add interactive filters.
A20: 6. From the PivotTable, go to Insert → Chart to create a PivotChart.
A21: 7. Copy the chart and paste it on the Dashboard sheet.
A22: 8. Connect all slicers to multiple charts using 'Report Connections'.
